sefaria_sdk/__init__.py
sefaria_sdk/client.py
sefaria_sdk/text_processing.py
sefaria_sdk-0.1.1.dist-info/licenses/LICENSE
tests/__init__.py
tests/conftest.py
tests/test_async_client.py
tests/test_client.py
tests/test_integration.py
tests/test_text_processing.py
sefaria_sdk-0.1.1.dist-info/METADATA
sefaria_sdk-0.1.1.dist-info/WHEEL
sefaria_sdk-0.1.1.dist-info/top_level.txt
sefaria_sdk-0.1.1.dist-info/RECORD
