Metadata-Version: 2.4
Name: sefaria-sdk
Version: 0.1.1
Summary: Unofficial Python SDK for the Sefaria API
Home-page: https://github.com/rbrtjns90/unofficial_sefaria_python_sdk
Author: Robert Jones
Author-email: 
Classifier: Programming Language :: Python :: 3
Classifier: License :: OSI Approved :: MIT License
Classifier: Operating System :: OS Independent
Requires-Python: >=3.7
License-File: LICENSE
Requires-Dist: requests>=2.31.0
Requires-Dist: python-dotenv>=1.0.0
Dynamic: author
Dynamic: classifier
Dynamic: description
Dynamic: description-content-type
Dynamic: home-page
Dynamic: license-file
Dynamic: requires-dist
Dynamic: requires-python
Dynamic: summary
